<annotation>
	<folder>emotion-confused</folder>
	<filename>18. uncertain-boss-young-man-face_1194-7951.jpg</filename>
	<path>/Users/connormccrt/Desktop/Hacklahoma/maymay_mood/data/emotion-confused/18. uncertain-boss-young-man-face_1194-7951.jpg</path>
	<source>
		<database>Unknown</database>
	</source>
	<size>
		<width>626</width>
		<height>417</height>
		<depth>3</depth>
	</size>
	<segmented>0</segmented>
	<object>
		<name>confused</name>
		<pose>Unspecified</pose>
		<truncated>0</truncated>
		<difficult>0</difficult>
		<bndbox>
			<xmin>268</xmin>
			<ymin>57</ymin>
			<xmax>350</xmax>
			<ymax>159</ymax>
		</bndbox>
	</object>
</annotation>
